concurrently/__init__.py
concurrently/_concurrently.py
concurrently/aux.py
concurrently/engines/__init__.py
concurrently/engines/asyncio.py
concurrently/engines/gevent.py
concurrently/engines/process.py
concurrently/engines/thread.py
tests/__init__.py
tests/engines/__init__.py
tests/engines/test_asyncio.py
tests/engines/test_asyncio_thread.py
tests/engines/test_gevent.py
tests/engines/test_process.py
tests/engines/test_thread.py
concurrently-2.dist-info/LICENSE
concurrently-2.dist-info/METADATA
concurrently-2.dist-info/WHEEL
concurrently-2.dist-info/top_level.txt
concurrently-2.dist-info/RECORD
