Metadata-Version: 2.1
Name: concurrently
Version: 2
Summary: Library helps easy write concurrent executed code blocks
Home-page: https://github.com/sirkonst/concurrently
Author: Konstantin Enchant
Author-email: sirkonst@gmail.com
Maintainer: Konstantin Enchant
Maintainer-email: sirkonst@gmail.com
Keywords: concurrent,thread,threading,process,multiprocessing,asyncio,gevent
Classifier: Development Status :: 5 - Production/Stable
Classifier: License :: OSI Approved :: MIT License
Classifier: Intended Audience :: Developers
Classifier: Natural Language :: English
Classifier: Natural Language :: Russian
Classifier: Operating System :: OS Independent
Classifier: Programming Language :: Python :: 3 :: Only
Classifier: Programming Language :: Python :: 3.7
Classifier: Programming Language :: Python :: 3.8
Classifier: Programming Language :: Python :: 3.9
Classifier: Programming Language :: Python :: 3.10
Classifier: Programming Language :: Python :: 3.11
Classifier: Programming Language :: Python :: 3.12
Classifier: Topic :: Software Development :: Libraries
Requires-Python: >=3.5
License-File: LICENSE
Provides-Extra: gevent
Requires-Dist: gevent; python_version < "3.8" and extra == "gevent"
Requires-Dist: gevent>=1.5a2; python_version >= "3.8" and extra == "gevent"
Provides-Extra: develop
Requires-Dist: mypy~=1.4; python_version < "3.8" and extra == "develop"
Requires-Dist: mypy~=1.5; python_version >= "3.8" and extra == "develop"
Requires-Dist: wheel~=0.41; extra == "develop"
Requires-Dist: twine~=4.0; extra == "develop"
Requires-Dist: tox~=3.28; python_version < "3.8" and extra == "develop"
Requires-Dist: tox~=4.11; python_version >= "3.8" and extra == "develop"
Requires-Dist: pytest~=7.4; extra == "develop"
Requires-Dist: pytest-asyncio~=0.21; extra == "develop"
Requires-Dist: pylama~=8.4; extra == "develop"
Requires-Dist: coverage~=6.2; python_version < "3.8" and extra == "develop"
Requires-Dist: coverage~=7.3; python_version >= "3.8" and extra == "develop"
Requires-Dist: Sphinx~=5.3; python_version < "3.9" and extra == "develop"
Requires-Dist: Sphinx~=7.2; python_version >= "3.9" and extra == "develop"
